sadedegel_icu-2.6.dist-info/RECORD
sadedegel_icu-2.6.dist-info/LICENSE
sadedegel_icu-2.6.dist-info/WHEEL
sadedegel_icu-2.6.dist-info/top_level.txt
sadedegel_icu-2.6.dist-info/METADATA
icu/__init__.py
icu/_icu.cpython-38-darwin.so
icu/.dylibs/libicudata.68.dylib
icu/.dylibs/libicui18n.68.dylib
icu/.dylibs/libicuuc.68.dylib
icu/.dylibs/libicutu.68.dylib
icu/.dylibs/libicuio.68.dylib
